oss_python_template/__init__.py
oss_python_template/main.py
oss_python_template-1.0.dist-info/LICENSE
oss_python_template-1.0.dist-info/METADATA
oss_python_template-1.0.dist-info/WHEEL
oss_python_template-1.0.dist-info/RECORD
